lars/__init__.py
lars/main.py
lars/controllers/__init__.py
lars/controllers/apps.py
lars/controllers/base.py
lars/controllers/parser.py
lars/core/__init__.py
lars/core/exc.py
lars/core/version.py
lars/ext/__init__.py
lars/plugins/__init__.py
lars/templates/__init__.py
lars/templates/command1.jinja2
lars/templates/container.jinja2
lars/templates/apps/list.jinja2
lars/templates/apps/list_empty.jinja2
lars/templates/apps/list_extended.jinja2
lars/utilities/__init__.py
lars/utilities/db_context.py
lars/utilities/sql_builder.py
lars/utilities/value_validator.py
ulars-1.0.9b0.dist-info/LICENSE
ulars-1.0.9b0.dist-info/LICENSE.md
ulars-1.0.9b0.dist-info/METADATA
ulars-1.0.9b0.dist-info/WHEEL
ulars-1.0.9b0.dist-info/entry_points.txt
ulars-1.0.9b0.dist-info/top_level.txt
ulars-1.0.9b0.dist-info/RECORD
