Metadata-Version: 2.1
Name: ulars
Version: 1.0.9b0
Summary: From txt to sqlite3 parser of logs
Home-page: https://github.com/Ujinjinjin/lars
Author: Camille Galladjov
Author-email: ujinjinjin@outlook.com
License: MIT
Platform: UNKNOWN
Requires-Dist: cement (==3.0.4)
Requires-Dist: jinja2
Requires-Dist: pyyaml
Requires-Dist: colorlog
Requires-Dist: tinydb
Requires-Dist: progress
Requires-Dist: PyYAML
